{
  "id": "post-how-to-use-capcut",
  "slug": "how-to-use-capcut",
  "status": "published",
  "bylines": [
    {
      "byline": "byline-tony"
    }
  ],
  "taxonomies": {
    "category": [
      "ia",
      "herramientas"
    ],
    "tag": [
      "tutorial"
    ]
  },
  "data": {
    "title": "CapCut Tutorial: Step-by-Step Video Editing Guide",
    "excerpt": "Master CapCut with this easy tutorial. From auto captions to viral templates, create stunning videos quickly. Start editing like a pro today!",
    "featured_image": {
      "$media": {
        "url": "https://tonyciencia.com/blog/how-to-use-capcut.jpg",
        "alt": "CapCut Tutorial: Step-by-Step Video Editing Guide",
        "filename": "how-to-use-capcut.jpg"
      }
    },
    "content": [
      {
        "_type": "block",
        "style": "h2",
        "markDefs": [],
        "children": [
          {
            "_type": "span",
            "text": "Introduction",
            "marks": []
          }
        ]
      },
      {
        "_type": "block",
        "style": "normal",
        "markDefs": [],
        "children": [
          {
            "_type": "span",
            "text": "Hey there, fellow creator! If you're looking to up your video game without the hassle, CapCut is your new best friend. This AI-powered editor from ByteDance has blown up for making pro-level editing a breeze, whether you're on mobile or desktop. I've been using it for months, and it's transformed how I produce content—saving time and boosting creativity. Ready to dive in? Let's get started with a simple step-by-step tutorial.",
            "marks": []
          }
        ]
      },
      {
        "_type": "block",
        "style": "normal",
        "markDefs": [
          {
            "_key": "l0",
            "_type": "link",
            "href": "https://capcutaffiliateprogram.pxf.io/c/6249333/1876054/2247"
          }
        ],
        "children": [
          {
            "_type": "span",
            "text": "First off, ",
            "marks": []
          },
          {
            "_type": "span",
            "text": "download CapCut for free",
            "marks": [
              "l0"
            ]
          },
          {
            "_type": "span",
            "text": " to follow along. It's quick and opens up a world of possibilities.",
            "marks": []
          }
        ]
      },
      {
        "_type": "block",
        "style": "h2",
        "markDefs": [],
        "children": [
          {
            "_type": "span",
            "text": "Step 1: Getting Started with CapCut",
            "marks": []
          }
        ]
      },
      {
        "_type": "block",
        "style": "normal",
        "markDefs": [
          {
            "_key": "l1",
            "_type": "link",
            "href": "https://capcut.com"
          }
        ],
        "children": [
          {
            "_type": "span",
            "text": "To begin, head to ",
            "marks": []
          },
          {
            "_type": "span",
            "text": "capcut.com",
            "marks": [
              "l1"
            ]
          },
          {
            "_type": "span",
            "text": " and grab the app for your device—iOS, Android, Windows, or Mac. The interface is super intuitive; you'll feel right at home even if you're new to editing. Start a new project by tapping the \"+\" button and importing your clips from your gallery or cloud storage. CapCut supports a ton of formats, so no compatibility headaches here.",
            "marks": []
          }
        ]
      },
      {
        "_type": "block",
        "style": "normal",
        "markDefs": [
          {
            "_key": "l2",
            "_type": "link",
            "href": "https://tonyciencia.com/en/posts/what-is-capcut"
          }
        ],
        "children": [
          {
            "_type": "span",
            "text": "If you're curious about its origins, check out ",
            "marks": []
          },
          {
            "_type": "span",
            "text": "what CapCut is",
            "marks": [
              "l2"
            ]
          },
          {
            "_type": "span",
            "text": " on our site for more details.",
            "marks": []
          }
        ]
      },
      {
        "_type": "block",
        "style": "h2",
        "markDefs": [],
        "children": [
          {
            "_type": "span",
            "text": "Step 2: Using Auto Captions and AI Tools",
            "marks": []
          }
        ]
      },
      {
        "_type": "block",
        "style": "normal",
        "markDefs": [],
        "children": [
          {
            "_type": "span",
            "text": "This is where CapCut shines. Go to the \"Text\" menu and select \"Auto Captions\"—it analyzes your audio and generates accurate subtitles in seconds. No more manual typing! The AI also offers features like background removal and scene detection, which I use to streamline my workflow. For instance, I recently edited a vlog where auto captions saved me over an hour.",
            "marks": []
          }
        ]
      },
      {
        "_type": "block",
        "style": "normal",
        "markDefs": [],
        "children": [
          {
            "_type": "span",
            "text": "Pro tip: Experiment with the AI-powered effects for dynamic transitions. It's like having a virtual editor assistant.",
            "marks": []
          }
        ]
      },
      {
        "_type": "block",
        "style": "h2",
        "markDefs": [],
        "children": [
          {
            "_type": "span",
            "text": "Step 3: Applying Effects and Templates",
            "marks": []
          }
        ]
      },
      {
        "_type": "block",
        "style": "normal",
        "markDefs": [],
        "children": [
          {
            "_type": "span",
            "text": "CapCut's library is packed with trendy templates and effects perfect for social media. Browse the \"Templates\" tab to find viral-style edits for TikTok or Instagram. Simply drag and drop your clips into a template, and it auto-adjusts timing and effects. I love how this helps me create polished content in minutes—no design skills needed.",
            "marks": []
          }
        ]
      },
      {
        "_type": "block",
        "style": "normal",
        "markDefs": [
          {
            "_key": "l3",
            "_type": "link",
            "href": "https://tonyciencia.com/en/posts/capcut-use-cases"
          }
        ],
        "children": [
          {
            "_type": "span",
            "text": "Want to see real-world applications? Explore ",
            "marks": []
          },
          {
            "_type": "span",
            "text": "use cases",
            "marks": [
              "l3"
            ]
          },
          {
            "_type": "span",
            "text": " for inspiration.",
            "marks": []
          }
        ]
      },
      {
        "_type": "block",
        "style": "h2",
        "markDefs": [],
        "children": [
          {
            "_type": "span",
            "text": "Step 4: Advanced Editing Tips",
            "marks": []
          }
        ]
      },
      {
        "_type": "block",
        "style": "normal",
        "markDefs": [],
        "children": [
          {
            "_type": "span",
            "text": "Once you're comfortable, dive into color correction and audio enhancements. Use the \"Adjust\" panel to tweak brightness, contrast, and saturation for that cinematic look. The audio tools let you add music, voiceovers, and sound effects seamlessly. I often use the AI clipper to trim long videos into highlights automatically—great for repurposing content.",
            "marks": []
          }
        ]
      },
      {
        "_type": "block",
        "style": "normal",
        "markDefs": [
          {
            "_key": "l4",
            "_type": "link",
            "href": "https://tonyciencia.com/en/posts/capcut-tips"
          }
        ],
        "children": [
          {
            "_type": "span",
            "text": "For deeper insights, our ",
            "marks": []
          },
          {
            "_type": "span",
            "text": "tips & best ways",
            "marks": [
              "l4"
            ]
          },
          {
            "_type": "span",
            "text": " guide has you covered.",
            "marks": []
          }
        ]
      },
      {
        "_type": "block",
        "style": "h2",
        "markDefs": [],
        "children": [
          {
            "_type": "span",
            "text": "Step 5: Exporting and Sharing",
            "marks": []
          }
        ]
      },
      {
        "_type": "block",
        "style": "normal",
        "markDefs": [
          {
            "_key": "l5",
            "_type": "link",
            "href": "https://capcutaffiliateprogram.pxf.io/c/6249333/1876054/2247"
          }
        ],
        "children": [
          {
            "_type": "span",
            "text": "When you're done, hit \"Export\" and choose your resolution—up to 4K for crisp quality. CapCut lets you share directly to platforms like YouTube, TikTok, or Instagram. The free version includes a small watermark, but it's barely noticeable. For watermark-free exports and more features, ",
            "marks": []
          },
          {
            "_type": "span",
            "text": "try CapCut Pro",
            "marks": [
              "l5"
            ]
          },
          {
            "_type": "span",
            "text": "—it's worth it for serious creators.",
            "marks": []
          }
        ]
      },
      {
        "_type": "block",
        "style": "h2",
        "markDefs": [],
        "children": [
          {
            "_type": "span",
            "text": "New Features Highlight",
            "marks": []
          }
        ]
      },
      {
        "_type": "block",
        "style": "normal",
        "markDefs": [
          {
            "_key": "l6",
            "_type": "link",
            "href": "https://tonyciencia.com/en/posts/capcut-new-features"
          }
        ],
        "children": [
          {
            "_type": "span",
            "text": "CapCut constantly rolls out updates that keep it ahead of the curve. Recent additions include enhanced AI scripts for auto-generating video outlines and improved template customization. I tested the new voice changer tool last week, and it added a fun twist to my tutorials. Stay updated by checking out ",
            "marks": []
          },
          {
            "_type": "span",
            "text": "new features",
            "marks": [
              "l6"
            ]
          },
          {
            "_type": "span",
            "text": " on TonyCiencia.",
            "marks": []
          }
        ]
      },
      {
        "_type": "block",
        "style": "h2",
        "markDefs": [],
        "children": [
          {
            "_type": "span",
            "text": "Who is CapCut Ideal For?",
            "marks": []
          }
        ]
      },
      {
        "_type": "block",
        "style": "normal",
        "markDefs": [
          {
            "_key": "l7",
            "_type": "link",
            "href": "https://tonyciencia.com/en/posts/why-choose-capcut"
          }
        ],
        "children": [
          {
            "_type": "span",
            "text": "This tool is perfect for beginners, social media influencers, marketers, and educators. Whether you're making quick reels, detailed tutorials, or promotional content, CapCut adapts to your needs. Its affordability and ease of use make it a standout—I've recommended it to friends who went from zero to confident editors in days. For more on why it's a top choice, see ",
            "marks": []
          },
          {
            "_type": "span",
            "text": "why choose CapCut",
            "marks": [
              "l7"
            ]
          },
          {
            "_type": "span",
            "text": ".",
            "marks": []
          }
        ]
      },
      {
        "_type": "block",
        "style": "h2",
        "markDefs": [],
        "children": [
          {
            "_type": "span",
            "text": "Conclusion",
            "marks": []
          }
        ]
      },
      {
        "_type": "block",
        "style": "normal",
        "markDefs": [
          {
            "_key": "l8",
            "_type": "link",
            "href": "https://capcutaffiliateprogram.pxf.io/c/6249333/1876054/2247"
          }
        ],
        "children": [
          {
            "_type": "span",
            "text": "CapCut has genuinely leveled up my content creation, and I bet it'll do the same for you. With its intuitive interface, powerful AI, and endless creative options, there's no reason not to give it a spin. Ready to create magic? ",
            "marks": []
          },
          {
            "_type": "span",
            "text": "Start editing with CapCut",
            "marks": [
              "l8"
            ]
          },
          {
            "_type": "span",
            "text": " and watch your videos come alive!",
            "marks": []
          }
        ]
      },
      {
        "_type": "block",
        "style": "h2",
        "markDefs": [],
        "children": [
          {
            "_type": "span",
            "text": "Keep reading on TonyCiencia",
            "marks": []
          }
        ]
      },
      {
        "_type": "block",
        "style": "normal",
        "markDefs": [
          {
            "_key": "l9",
            "_type": "link",
            "href": "https://tonyciencia.com/en/posts/what-is-capcut"
          }
        ],
        "children": [
          {
            "_type": "span",
            "text": "What is CapCut?",
            "marks": [
              "l9"
            ]
          }
        ],
        "listItem": "bullet",
        "level": 1
      },
      {
        "_type": "block",
        "style": "normal",
        "markDefs": [
          {
            "_key": "l10",
            "_type": "link",
            "href": "https://tonyciencia.com/en/posts/capcut-use-cases"
          }
        ],
        "children": [
          {
            "_type": "span",
            "text": "CapCut Use Cases",
            "marks": [
              "l10"
            ]
          }
        ],
        "listItem": "bullet",
        "level": 1
      },
      {
        "_type": "block",
        "style": "normal",
        "markDefs": [
          {
            "_key": "l11",
            "_type": "link",
            "href": "https://tonyciencia.com/en/posts/capcut-tips"
          }
        ],
        "children": [
          {
            "_type": "span",
            "text": "Tips & Best Ways to Use CapCut",
            "marks": [
              "l11"
            ]
          }
        ],
        "listItem": "bullet",
        "level": 1
      },
      {
        "_type": "block",
        "style": "normal",
        "markDefs": [
          {
            "_key": "l12",
            "_type": "link",
            "href": "https://tonyciencia.com/en/posts/why-choose-capcut"
          }
        ],
        "children": [
          {
            "_type": "span",
            "text": "Why Choose CapCut",
            "marks": [
              "l12"
            ]
          }
        ],
        "listItem": "bullet",
        "level": 1
      },
      {
        "_type": "block",
        "style": "normal",
        "markDefs": [
          {
            "_key": "l13",
            "_type": "link",
            "href": "https://tonyciencia.com/en/posts/how-to-use-elevenlabs"
          }
        ],
        "children": [
          {
            "_type": "span",
            "text": "How to Use ElevenLabs",
            "marks": [
              "l13"
            ]
          }
        ],
        "listItem": "bullet",
        "level": 1
      },
      {
        "_type": "block",
        "style": "normal",
        "markDefs": [
          {
            "_key": "l14",
            "_type": "link",
            "href": "https://tonyciencia.com/en/posts/how-to-use-descript"
          }
        ],
        "children": [
          {
            "_type": "span",
            "text": "How to Use Descript",
            "marks": [
              "l14"
            ]
          }
        ],
        "listItem": "bullet",
        "level": 1
      }
    ],
    "schema_type": "BlogPosting",
    "key_entities": "CapCut, ByteDance, video editing, content creators",
    "keywords": [
      "CapCut",
      "video editing tutorial",
      "AI video editor",
      "content creation",
      "auto captions",
      "step-by-step guide"
    ],
    "image_prompt": "Editorial tech thumbnail, 16:9. Incorporate the brand logo fetched from https://logo.clearbit.com/capcut.com as the clean focal element over a soft amber-to-cream gradient (Notion + Apple aesthetic). A creator on a laptop editing a vibrant video with auto captions and colorful effects overlaying the screen.. Glassmorphism cards, soft volumetric light, generous negative space for a title, no embedded text, no watermark. --ar 16:9 --style raw",
    "faq_items": [
      {
        "_type": "block",
        "style": "h3",
        "markDefs": [],
        "children": [
          {
            "_type": "span",
            "text": "Is CapCut free to use?",
            "marks": []
          }
        ]
      },
      {
        "_type": "block",
        "style": "normal",
        "markDefs": [],
        "children": [
          {
            "_type": "span",
            "text": "Yes, CapCut offers a free version packed with essential features like auto captions and basic effects. For advanced tools and no watermarks, you can upgrade to CapCut Pro.",
            "marks": []
          }
        ]
      },
      {
        "_type": "block",
        "style": "h3",
        "markDefs": [],
        "children": [
          {
            "_type": "span",
            "text": "Can I use CapCut on multiple devices?",
            "marks": []
          }
        ]
      },
      {
        "_type": "block",
        "style": "normal",
        "markDefs": [],
        "children": [
          {
            "_type": "span",
            "text": "Absolutely! CapCut is available on iOS, Android, Windows, and Mac, with seamless syncing so you can start editing on one device and continue on another.",
            "marks": []
          }
        ]
      },
      {
        "_type": "block",
        "style": "h3",
        "markDefs": [],
        "children": [
          {
            "_type": "span",
            "text": "How does CapCut's AI help in video editing?",
            "marks": []
          }
        ]
      },
      {
        "_type": "block",
        "style": "normal",
        "markDefs": [],
        "children": [
          {
            "_type": "span",
            "text": "CapCut's AI automates tasks like generating captions, removing backgrounds, and suggesting edits, which speeds up the process and lets you focus on creativity.",
            "marks": []
          }
        ]
      }
    ],
    "external_id": "tonyciencia-affiliate:en:capcut:tutorial",
    "source": "sdk-agent-blog-seo:mimo",
    "translation_of": "como-usar-capcut"
  },
  "published_at": "2026-06-12T04:59:04",
  "locale": "en"
}