{
  "id": "post-por-que-elegir-beautiful-ai",
  "slug": "por-que-elegir-beautiful-ai",
  "status": "published",
  "bylines": [
    {
      "byline": "byline-tony"
    }
  ],
  "taxonomies": {
    "category": [
      "ia",
      "herramientas"
    ],
    "tag": [
      "opinion"
    ]
  },
  "data": {
    "title": "Beautiful.ai: Presentaciones con IA que se diseñan solas",
    "excerpt": "Descubre cómo Beautiful.ai transforma tu contenido en presentaciones profesionales en minutos. Prueba gratis y olvídate del diseño manual.",
    "featured_image": {
      "$media": {
        "url": "https://tonyciencia.com/blog/por-que-elegir-beautiful-ai.jpg",
        "alt": "Beautiful.ai: Presentaciones con IA que se diseñan solas",
        "filename": "por-que-elegir-beautiful-ai.jpg"
      }
    },
    "content": [
      {
        "_type": "block",
        "style": "h2",
        "markDefs": [],
        "children": [
          {
            "_type": "span",
            "text": "¿Te suena familiar? El dolor de diseñar presentaciones",
            "marks": []
          }
        ]
      },
      {
        "_type": "block",
        "style": "normal",
        "markDefs": [
          {
            "_key": "l0",
            "_type": "link",
            "href": "https://beautifulai.partnerlinks.io/a9w9832hbrbt"
          }
        ],
        "children": [
          {
            "_type": "span",
            "text": "Son las 10 de la noche. Tienes la información lista para esa reunión crucial de mañana, pero pasas horas peleándote con PowerPoint: alinear textos, elegir fuentes, ajustar imágenes que no encajan. El resultado final se ve... amateur. ",
            "marks": []
          },
          {
            "_type": "span",
            "text": "Beautiful.ai",
            "marks": [
              "strong"
            ]
          },
          {
            "_type": "span",
            "text": " nace para eliminar esa frustración de raíz. Esta no es una herramienta más para crear diapositivas; es un asistente de diseño impulsado por IA que trabaja para ti mientras tú te concentras en el mensaje. Imagina agregar tu contenido y que, automáticamente, la herramienta cree un layout profesional, con espaciado perfecto y armonía visual. Esa es la promesa que cumple Beautiful.ai, y en esta reseña te explico por qué está ganando adeptos a un ritmo vertiginoso. Si quieres probarla, ",
            "marks": []
          },
          {
            "_type": "span",
            "text": "puedes empezar tu prueba gratuita de 14 días aquí",
            "marks": [
              "l0"
            ]
          },
          {
            "_type": "span",
            "text": ".",
            "marks": []
          }
        ]
      },
      {
        "_type": "block",
        "style": "normal",
        "markDefs": [],
        "children": [
          {
            "_type": "span",
            "text": "*Divulgación: Este artículo contiene enlaces de afiliado. Si compras a través de ellos, no pagas extra y ayudas a mantener TonyCiencia.*",
            "marks": []
          }
        ]
      },
      {
        "_type": "block",
        "style": "h2",
        "markDefs": [],
        "children": [
          {
            "_type": "span",
            "text": "Cómo funciona la magia: la IA que diseña en tiempo real",
            "marks": []
          }
        ]
      },
      {
        "_type": "block",
        "style": "normal",
        "markDefs": [],
        "children": [
          {
            "_type": "span",
            "text": "El núcleo de Beautiful.ai es su tecnología ",
            "marks": []
          },
          {
            "_type": "span",
            "text": "Smart Slides",
            "marks": [
              "strong"
            ]
          },
          {
            "_type": "span",
            "text": ". A diferencia de las plantillas estáticas de toda la vida, aquí la IA entiende la estructura de tu contenido. Empiezas por crear una nueva presentación y eliges un \"Tipo de Slide\" (como \"Título y subtítulo\", \"Dos columnas con imagen\", o \"Gráfico con leyenda\"). Luego, simplemente escribes o pegas tu texto, y subes tus imágenes. ",
            "marks": []
          },
          {
            "_type": "span",
            "text": "La IA se encarga del resto.",
            "marks": [
              "strong"
            ]
          }
        ]
      },
      {
        "_type": "block",
        "style": "normal",
        "markDefs": [
          {
            "_key": "l1",
            "_type": "link",
            "href": "https://tonyciencia.com/posts/como-usar-beautiful-ai"
          }
        ],
        "children": [
          {
            "_type": "span",
            "text": "Si reduces un párrafo, la diapositiva se reajusta. Si agregas una imagen más, el layout se reorganiza de forma inteligente para que todo encaje sin que tú muevas un solo pixel. Esto es revolucionario porque libera tu energía creativa. En lugar de ser un \"operador de software\", te conviertes en el director de la historia. La IA mantiene un diseño consistente y profesional en toda la presentación, algo que para la mayoría es un reto titánico. Para ver un tutorial paso a paso de este proceso, te recomiendo nuestra guía ",
            "marks": []
          },
          {
            "_type": "span",
            "text": "cómo usar Beautiful.ai",
            "marks": [
              "l1"
            ]
          },
          {
            "_type": "span",
            "text": ".",
            "marks": []
          }
        ]
      },
      {
        "_type": "block",
        "style": "h2",
        "markDefs": [],
        "children": [
          {
            "_type": "span",
            "text": "Funciones nuevas y destacadas que te van a encantar",
            "marks": []
          }
        ]
      },
      {
        "_type": "block",
        "style": "normal",
        "markDefs": [],
        "children": [
          {
            "_type": "span",
            "text": "Beautiful.ai no se estanca. Su equipo está constantemente innovando. Algunas de las características que más destacan actualmente incluyen:",
            "marks": []
          }
        ]
      },
      {
        "_type": "block",
        "style": "normal",
        "markDefs": [],
        "children": [
          {
            "_type": "span",
            "text": "Generación de Contenido con IA:",
            "marks": [
              "strong"
            ]
          },
          {
            "_type": "span",
            "text": " Ahora puedes pedirle a la IA que genere textos, esquemas o ideas para tus slides directamente desde la plataforma. Es como tener un consultor de contenido integrado que te ayuda a superar el bloqueo del escritor.",
            "marks": []
          }
        ],
        "listItem": "bullet",
        "level": 1
      },
      {
        "_type": "block",
        "style": "normal",
        "markDefs": [],
        "children": [
          {
            "_type": "span",
            "text": "Mejoras en los Smart Slides:",
            "marks": [
              "strong"
            ]
          },
          {
            "_type": "span",
            "text": " Los algoritmos de diseño se refinan, ofreciendo transiciones más suaves y diseños más modernos. La IA ahora \"entiende\" mejor el contexto de tu presentación para sugerir layouts aún más relevantes.",
            "marks": []
          }
        ],
        "listItem": "bullet",
        "level": 1
      },
      {
        "_type": "block",
        "style": "normal",
        "markDefs": [],
        "children": [
          {
            "_type": "span",
            "text": "Colaboración en Tiempo Real:",
            "marks": [
              "strong"
            ]
          },
          {
            "_type": "span",
            "text": " Trabaja con tu equipo simultáneamente en la misma presentación, viendo los cambios en vivo. Perfecto para equipos remotos o departamentos que necesitan alinear mensajes.",
            "marks": []
          }
        ],
        "listItem": "bullet",
        "level": 1
      },
      {
        "_type": "block",
        "style": "normal",
        "markDefs": [],
        "children": [
          {
            "_type": "span",
            "text": "Exportación Mejorada:",
            "marks": [
              "strong"
            ]
          },
          {
            "_type": "span",
            "text": " Opciones más robustas para exportar a PDF, PowerPoint, o incluso compartir un enlace interactivo, manteniendo toda la calidad visual.",
            "marks": []
          }
        ],
        "listItem": "bullet",
        "level": 1
      },
      {
        "_type": "block",
        "style": "normal",
        "markDefs": [
          {
            "_key": "l2",
            "_type": "link",
            "href": "https://tonyciencia.com/posts/beautiful-ai-novedades"
          }
        ],
        "children": [
          {
            "_type": "span",
            "text": "Para estar al tanto de todas las novedades, te sugiero visitar nuestra sección dedicada a las ",
            "marks": []
          },
          {
            "_type": "span",
            "text": "novedades de Beautiful.ai",
            "marks": [
              "l2"
            ]
          },
          {
            "_type": "span",
            "text": ". La velocidad a la que evoluciona es impresionante.",
            "marks": []
          }
        ]
      },
      {
        "_type": "block",
        "style": "h2",
        "markDefs": [],
        "children": [
          {
            "_type": "span",
            "text": "¿Para quién es ideal Beautiful.ai? (Spoiler: Para casi todos)",
            "marks": []
          }
        ]
      },
      {
        "_type": "block",
        "style": "normal",
        "markDefs": [],
        "children": [
          {
            "_type": "span",
            "text": "Esta herramienta es increíblemente versátil, pero brilla especialmente en estos perfiles:",
            "marks": []
          }
        ]
      },
      {
        "_type": "block",
        "style": "normal",
        "markDefs": [
          {
            "_key": "l3",
            "_type": "link",
            "href": "https://beautifulai.partnerlinks.io/a9w9832hbrbt"
          }
        ],
        "children": [
          {
            "_type": "span",
            "text": "Emprendedores y Dueños de Pequeños Negocios:",
            "marks": [
              "strong"
            ]
          },
          {
            "_type": "span",
            "text": " Si necesitas crear pitches para inversores, propuestas comerciales o presentaciones para clientes, pero no tienes presupuesto para un diseñador. Beautiful.ai te da un acabado de agencia a una fracción del costo. ",
            "marks": []
          },
          {
            "_type": "span",
            "text": "Empieza a crear presentaciones que cierren negocios",
            "marks": [
              "l3"
            ]
          },
          {
            "_type": "span",
            "text": ".",
            "marks": []
          }
        ],
        "listItem": "bullet",
        "level": 1
      },
      {
        "_type": "block",
        "style": "normal",
        "markDefs": [],
        "children": [
          {
            "_type": "span",
            "text": "Profesionales de Marketing y Ventas:",
            "marks": [
              "strong"
            ]
          },
          {
            "_type": "span",
            "text": " Para quienes necesitan crear materiales de alto impacto rápidamente. Reportes de campañas, presentaciones de producto, o decks para conferencias se crean en un santiamén.",
            "marks": []
          }
        ],
        "listItem": "bullet",
        "level": 1
      },
      {
        "_type": "block",
        "style": "normal",
        "markDefs": [],
        "children": [
          {
            "_type": "span",
            "text": "Educadores y Académicos:",
            "marks": [
              "strong"
            ]
          },
          {
            "_type": "span",
            "text": " Transforma tus clases o conferencias. Explicar conceptos complejos con slides visuales y claras se vuelve una tarea sencilla.",
            "marks": []
          }
        ],
        "listItem": "bullet",
        "level": 1
      },
      {
        "_type": "block",
        "style": "normal",
        "markDefs": [],
        "children": [
          {
            "_type": "span",
            "text": "Equipos de Productos y Startups:",
            "marks": [
              "strong"
            ]
          },
          {
            "_type": "span",
            "text": " Ideal para la creación de roadmaps, presentaciones de actualizaciones de producto (release notes) y alinear a todo el equipo con una visión visual clara.",
            "marks": []
          }
        ],
        "listItem": "bullet",
        "level": 1
      },
      {
        "_type": "block",
        "style": "normal",
        "markDefs": [
          {
            "_key": "l4",
            "_type": "link",
            "href": "https://tonyciencia.com/posts/beautiful-ai-casos-de-uso"
          }
        ],
        "children": [
          {
            "_type": "span",
            "text": "Si te identificas con alguno de estos roles, merece la pena echarle un vistazo. Revisa estos ",
            "marks": []
          },
          {
            "_type": "span",
            "text": "casos de uso específicos",
            "marks": [
              "l4"
            ]
          },
          {
            "_type": "span",
            "text": " para inspirarte.",
            "marks": []
          }
        ]
      },
      {
        "_type": "block",
        "style": "h2",
        "markDefs": [],
        "children": [
          {
            "_type": "span",
            "text": "Planes y Precios: Inversión que se paga sola",
            "marks": []
          }
        ]
      },
      {
        "_type": "block",
        "style": "normal",
        "markDefs": [],
        "children": [
          {
            "_type": "span",
            "text": "Beautiful.ai ofrece un modelo de suscripción claro. El plan ",
            "marks": []
          },
          {
            "_type": "span",
            "text": "Pro",
            "marks": [
              "strong"
            ]
          },
          {
            "_type": "span",
            "text": ", pensado para individuos, tiene un costo muy competitivo. A cambio, obtienes acceso a todas las funciones de IA, plantillas ilimitadas, y la capacidad de crear presentaciones ilimitadas. La velocidad y la calidad del output ahorran horas de trabajo, lo que se traduce en un retorno de inversión casi inmediato en productividad.",
            "marks": []
          }
        ]
      },
      {
        "_type": "block",
        "style": "normal",
        "markDefs": [
          {
            "_key": "l5",
            "_type": "link",
            "href": "https://beautifulai.partnerlinks.io/a9w9832hbrbt"
          }
        ],
        "children": [
          {
            "_type": "span",
            "text": "Existe también un plan Team para organizaciones, con funciones adicionales de gestión y colaboración. Puedes probar la plataforma sin riesgo con su ",
            "marks": []
          },
          {
            "_type": "span",
            "text": "prueba gratuita de 14 días",
            "marks": [
              "strong"
            ]
          },
          {
            "_type": "span",
            "text": ", que te da acceso completo al plan Pro. Es la mejor forma de experimentar la \"magia\" por ti mismo. ¿Listo para dejar de sufrir con el diseño? ",
            "marks": []
          },
          {
            "_type": "span",
            "text": "Comienza tu prueba gratuita ahora",
            "marks": [
              "l5"
            ]
          },
          {
            "_type": "span",
            "text": ".",
            "marks": []
          }
        ]
      },
      {
        "_type": "block",
        "style": "h2",
        "markDefs": [],
        "children": [
          {
            "_type": "span",
            "text": "Consejos Pro para sacar el máximo partido",
            "marks": []
          }
        ]
      },
      {
        "_type": "block",
        "style": "normal",
        "markDefs": [],
        "children": [
          {
            "_type": "span",
            "text": "Una vez que la tengas, aquí van algunos trucos para potenciar tu experiencia:",
            "marks": []
          }
        ]
      },
      {
        "_type": "block",
        "style": "normal",
        "markDefs": [],
        "children": [
          {
            "_type": "span",
            "text": "1. ",
            "marks": []
          },
          {
            "_type": "span",
            "text": "Empieza con una estructura clara:",
            "marks": [
              "strong"
            ]
          },
          {
            "_type": "span",
            "text": " Antes de abrir la herramienta, ten en un documento la jerarquía de tu información. La IA es genial organizando, pero tú eres el estratega.",
            "marks": []
          }
        ]
      },
      {
        "_type": "block",
        "style": "normal",
        "markDefs": [],
        "children": [
          {
            "_type": "span",
            "text": "2. ",
            "marks": []
          },
          {
            "_type": "span",
            "text": "Usa el panel de \"Smart Slide\":",
            "marks": [
              "strong"
            ]
          },
          {
            "_type": "span",
            "text": " No te limites al tipo de slide inicial. Puedes cambiar el layout en cualquier momento desde el panel derecho y la IA reestructurará todo de forma coherente.",
            "marks": []
          }
        ]
      },
      {
        "_type": "block",
        "style": "normal",
        "markDefs": [],
        "children": [
          {
            "_type": "span",
            "text": "3. ",
            "marks": []
          },
          {
            "_type": "span",
            "text": "Aprovecha los atajos de teclado:",
            "marks": [
              "strong"
            ]
          },
          {
            "_type": "span",
            "text": " Son súper intuitivos para navegar y editar más rápido.",
            "marks": []
          }
        ]
      },
      {
        "_type": "block",
        "style": "normal",
        "markDefs": [],
        "children": [
          {
            "_type": "span",
            "text": "4. ",
            "marks": []
          },
          {
            "_type": "span",
            "text": "Explora el catálogo de iconos y fotos:",
            "marks": [
              "strong"
            ]
          },
          {
            "_type": "span",
            "text": " Beautiful.ai incluye una biblioteca integrada de recursos que se adaptan perfectamente al estilo de tu presentación.",
            "marks": []
          }
        ]
      },
      {
        "_type": "block",
        "style": "normal",
        "markDefs": [
          {
            "_key": "l6",
            "_type": "link",
            "href": "https://tonyciencia.com/posts/trucos-beautiful-ai"
          }
        ],
        "children": [
          {
            "_type": "span",
            "text": "Para más trucos avanzados y mejores prácticas, no te pierdes nuestros ",
            "marks": []
          },
          {
            "_type": "span",
            "text": "trucos para Beautiful.ai",
            "marks": [
              "l6"
            ]
          },
          {
            "_type": "span",
            "text": ". Son consejos que marcan la diferencia entre una buena presentación y una extraordinaria.",
            "marks": []
          }
        ]
      },
      {
        "_type": "block",
        "style": "h2",
        "markDefs": [],
        "children": [
          {
            "_type": "span",
            "text": "¿Cómo se compara? Su lugar en el ecosistema de herramientas de IA",
            "marks": []
          }
        ]
      },
      {
        "_type": "block",
        "style": "normal",
        "markDefs": [
          {
            "_key": "l7",
            "_type": "link",
            "href": "https://tonyciencia.com/posts/como-usar-gamma"
          },
          {
            "_key": "l8",
            "_type": "link",
            "href": "https://tonyciencia.com/posts/como-usar-descript"
          },
          {
            "_key": "l9",
            "_type": "link",
            "href": "https://tonyciencia.com/posts/como-usar-elevenlabs"
          }
        ],
        "children": [
          {
            "_type": "span",
            "text": "En un mar de herramientas, Beautiful.ai se define por su enfoque específico: ",
            "marks": []
          },
          {
            "_type": "span",
            "text": "la creación de presentaciones visuales de alta calidad con el menor esfuerzo posible.",
            "marks": [
              "strong"
            ]
          },
          {
            "_type": "span",
            "text": " Mientras que herramientas como ",
            "marks": []
          },
          {
            "_type": "span",
            "text": "Gamma",
            "marks": [
              "l7"
            ]
          },
          {
            "_type": "span",
            "text": " son excelentes para generar borradores rápidos y narrativas interactivas, y plataformas como ",
            "marks": []
          },
          {
            "_type": "span",
            "text": "Descript",
            "marks": [
              "l8"
            ]
          },
          {
            "_type": "span",
            "text": " o ",
            "marks": []
          },
          {
            "_type": "span",
            "text": "ElevenLabs",
            "marks": [
              "l9"
            ]
          },
          {
            "_type": "span",
            "text": " dominan el ámbito del audio y video, Beautiful.ai es el campeón indiscutible cuando el objetivo final es una ",
            "marks": []
          },
          {
            "_type": "span",
            "text": "presentación de diapositivas visualmente impactante y profesional",
            "marks": [
              "strong"
            ]
          },
          {
            "_type": "span",
            "text": ". Su IA está finamente calibrada para el diseño gráfico y el layout, un nicho donde supera a los generalistas.",
            "marks": []
          }
        ]
      },
      {
        "_type": "block",
        "style": "normal",
        "markDefs": [
          {
            "_key": "l10",
            "_type": "link",
            "href": "https://tonyciencia.com/posts/que-es-beautiful-ai"
          }
        ],
        "children": [
          {
            "_type": "span",
            "text": "Si aún no estás seguro de qué herramienta necesitas, nuestra guía sobre ",
            "marks": []
          },
          {
            "_type": "span",
            "text": "qué es Beautiful.ai y para qué sirve",
            "marks": [
              "l10"
            ]
          },
          {
            "_type": "span",
            "text": " te ayudará a aclararlo.",
            "marks": []
          }
        ]
      },
      {
        "_type": "block",
        "style": "h2",
        "markDefs": [],
        "children": [
          {
            "_type": "span",
            "text": "Preguntas Frecuentes (FAQ)",
            "marks": []
          }
        ]
      },
      {
        "_type": "block",
        "style": "normal",
        "markDefs": [],
        "children": [
          {
            "_type": "span",
            "text": "¿Puedo usar Beautiful.ai para trabajo comercial o presentaciones para clientes?",
            "marks": [
              "strong"
            ]
          }
        ]
      },
      {
        "_type": "block",
        "style": "normal",
        "markDefs": [],
        "children": [
          {
            "_type": "span",
            "text": "¡Absolutamente! De hecho, es uno de sus puntos más fuertes. Los diseños resultantes son de calidad profesional y están pensados para entornos corporativos y comerciales. Puedes usarlo para crear propuestas, reportes y decks de venta sin problemas.",
            "marks": []
          }
        ]
      },
      {
        "_type": "block",
        "style": "normal",
        "markDefs": [],
        "children": [
          {
            "_type": "span",
            "text": "¿Necesito saber de diseño para usarla?",
            "marks": [
              "strong"
            ]
          }
        ]
      },
      {
        "_type": "block",
        "style": "normal",
        "markDefs": [],
        "children": [
          {
            "_type": "span",
            "text": "No en absoluto. Ese es precisamente el mayor beneficio. La IA se encarga de todo el trabajo técnico del diseño. Tú solo necesitas saber qué quieres comunicar; la herramienta te ayuda a comunicarlo de la forma más atractiva.",
            "marks": []
          }
        ]
      },
      {
        "_type": "block",
        "style": "normal",
        "markDefs": [],
        "children": [
          {
            "_type": "span",
            "text": "¿Mis presentaciones se ven \"genéricas\" o como una plantilla evidente?",
            "marks": [
              "strong"
            ]
          }
        ]
      },
      {
        "_type": "block",
        "style": "normal",
        "markDefs": [],
        "children": [
          {
            "_type": "span",
            "text": "Este es un temor común, pero infundado. Beautiful.ai utiliza cientos de combinaciones de estilos, colores y layouts. La personalización que logras con tu propio contenido (texto, imágenes, marca) hace que cada presentación sea única. La IA evita el aspecto de \"plantilla estática\".",
            "marks": []
          }
        ]
      },
      {
        "_type": "block",
        "style": "normal",
        "markDefs": [],
        "children": [
          {
            "_type": "span",
            "text": "¿Puedo importar/exportar desde PowerPoint?",
            "marks": [
              "strong"
            ]
          }
        ]
      },
      {
        "_type": "block",
        "style": "normal",
        "markDefs": [],
        "children": [
          {
            "_type": "span",
            "text": "Sí. Puedes importar archivos .pptx existentes para darles un lavado de cara con la IA de Beautiful.ai, y luego exportar tus creaciones de vuelta a PowerPoint si lo necesitas, además de PDF y otros formatos.",
            "marks": []
          }
        ]
      },
      {
        "_type": "block",
        "style": "h2",
        "markDefs": [],
        "children": [
          {
            "_type": "span",
            "text": "Sigue leyendo en TonyCiencia",
            "marks": []
          }
        ]
      },
      {
        "_type": "block",
        "style": "normal",
        "markDefs": [],
        "children": [
          {
            "_type": "span",
            "text": "¿Te ha gustado esta herramienta? Profundiza más con nuestros artículos:",
            "marks": []
          }
        ]
      },
      {
        "_type": "block",
        "style": "normal",
        "markDefs": [
          {
            "_key": "l11",
            "_type": "link",
            "href": "https://tonyciencia.com/posts/como-usar-beautiful-ai"
          }
        ],
        "children": [
          {
            "_type": "span",
            "text": "Tutorial paso a paso: Cómo usar Beautiful.ai",
            "marks": [
              "l11"
            ]
          }
        ],
        "listItem": "bullet",
        "level": 1
      },
      {
        "_type": "block",
        "style": "normal",
        "markDefs": [
          {
            "_key": "l12",
            "_type": "link",
            "href": "https://tonyciencia.com/posts/beautiful-ai-novedades"
          }
        ],
        "children": [
          {
            "_type": "span",
            "text": "Todas las novedades y actualizaciones de Beautiful.ai",
            "marks": [
              "l12"
            ]
          }
        ],
        "listItem": "bullet",
        "level": 1
      },
      {
        "_type": "block",
        "style": "normal",
        "markDefs": [
          {
            "_key": "l13",
            "_type": "link",
            "href": "https://tonyciencia.com/posts/beautiful-ai-casos-de-uso"
          }
        ],
        "children": [
          {
            "_type": "span",
            "text": "Casos de uso reales y ejemplos",
            "marks": [
              "l13"
            ]
          }
        ],
        "listItem": "bullet",
        "level": 1
      },
      {
        "_type": "block",
        "style": "normal",
        "markDefs": [
          {
            "_key": "l14",
            "_type": "link",
            "href": "https://tonyciencia.com/posts/trucos-beautiful-ai"
          }
        ],
        "children": [
          {
            "_type": "span",
            "text": "Trucos avanzados y mejores prácticas",
            "marks": [
              "l14"
            ]
          }
        ],
        "listItem": "bullet",
        "level": 1
      },
      {
        "_type": "block",
        "style": "normal",
        "markDefs": [
          {
            "_key": "l15",
            "_type": "link",
            "href": "https://tonyciencia.com/posts/que-es-beautiful-ai"
          }
        ],
        "children": [
          {
            "_type": "span",
            "text": "¿Qué es exactamente Beautiful.ai?",
            "marks": [
              "l15"
            ]
          }
        ],
        "listItem": "bullet",
        "level": 1
      },
      {
        "_type": "block",
        "style": "normal",
        "markDefs": [
          {
            "_key": "l16",
            "_type": "link",
            "href": "https://tonyciencia.com/posts/como-usar-elevenlabs"
          },
          {
            "_key": "l17",
            "_type": "link",
            "href": "https://tonyciencia.com/posts/como-usar-descript"
          },
          {
            "_key": "l18",
            "_type": "link",
            "href": "https://tonyciencia.com/posts/como-usar-gamma"
          }
        ],
        "children": [
          {
            "_type": "span",
            "text": "Y si te interesa el mundo de la creación de contenido con IA, no te pierdas nuestras guías sobre herramientas complementarias como ",
            "marks": []
          },
          {
            "_type": "span",
            "text": "ElevenLabs",
            "marks": [
              "l16"
            ]
          },
          {
            "_type": "span",
            "text": ", ",
            "marks": []
          },
          {
            "_type": "span",
            "text": "Descript",
            "marks": [
              "l17"
            ]
          },
          {
            "_type": "span",
            "text": " o ",
            "marks": []
          },
          {
            "_type": "span",
            "text": "Gamma",
            "marks": [
              "l18"
            ]
          },
          {
            "_type": "span",
            "text": ".",
            "marks": []
          }
        ]
      }
    ],
    "schema_type": "BlogPosting",
    "key_entities": "Beautiful.ai, AI, Presentaciones, Smart Slides",
    "keywords": [
      "Beautiful.ai",
      "presentaciones con IA",
      "herramienta presentaciones",
      "software diseño slides",
      "IA presentaciones"
    ],
    "image_prompt": "Editorial tech thumbnail, 16:9. Incorporate the brand logo fetched from https://logo.clearbit.com/beautiful.ai as the clean focal element over a soft amber-to-cream gradient (Notion + Apple aesthetic). A modern laptop on a wooden desk displaying colorful, professionally designed presentation slides with an abstract AI brain visualization overlaying the screen.. Glassmorphism cards, soft volumetric light, generous negative space for a title, no embedded text, no watermark. --ar 16:9 --style raw",
    "faq_items": [
      {
        "_type": "block",
        "style": "h3",
        "markDefs": [],
        "children": [
          {
            "_type": "span",
            "text": "¿Puedo usar Beautiful.ai para trabajo comercial o presentaciones para clientes?",
            "marks": []
          }
        ]
      },
      {
        "_type": "block",
        "style": "normal",
        "markDefs": [],
        "children": [
          {
            "_type": "span",
            "text": "¡Absolutamente! De hecho, es uno de sus puntos más fuertes. Los diseños resultantes son de calidad profesional y están pensados para entornos corporativos y comerciales. Puedes usarlo para crear propuestas, reportes y decks de venta sin problemas.",
            "marks": []
          }
        ]
      },
      {
        "_type": "block",
        "style": "h3",
        "markDefs": [],
        "children": [
          {
            "_type": "span",
            "text": "¿Necesito saber de diseño para usarla?",
            "marks": []
          }
        ]
      },
      {
        "_type": "block",
        "style": "normal",
        "markDefs": [],
        "children": [
          {
            "_type": "span",
            "text": "No en absoluto. Ese es precisamente el mayor beneficio. La IA se encarga de todo el trabajo técnico del diseño. Tú solo necesitas saber qué quieres comunicar; la herramienta te ayuda a comunicarlo de la forma más atractiva.",
            "marks": []
          }
        ]
      },
      {
        "_type": "block",
        "style": "h3",
        "markDefs": [],
        "children": [
          {
            "_type": "span",
            "text": "¿Mis presentaciones se ven \"genéricas\" o como una plantilla evidente?",
            "marks": []
          }
        ]
      },
      {
        "_type": "block",
        "style": "normal",
        "markDefs": [],
        "children": [
          {
            "_type": "span",
            "text": "Este es un temor común, pero infundado. Beautiful.ai utiliza cientos de combinaciones de estilos, colores y layouts. La personalización que logras con tu propio contenido (texto, imágenes, marca) hace que cada presentación sea única. La IA evita el aspecto de \"plantilla estática\".",
            "marks": []
          }
        ]
      }
    ],
    "external_id": "tonyciencia-affiliate:es:beautiful-ai:porque",
    "source": "sdk-agent-blog-seo:mimo"
  },
  "published_at": "2026-06-12T05:20:03",
  "locale": "es"
}